ai_podcast_generator/__init__.py
ai_podcast_generator/podcast_generator.py
ai_podcast_generator/prompts.py
ai_podcast_generator/utils.py
ai_podcast_generator-0.1.0.dist-info/licenses/LICENSE
ai_podcast_generator-0.1.0.dist-info/METADATA
ai_podcast_generator-0.1.0.dist-info/WHEEL
ai_podcast_generator-0.1.0.dist-info/top_level.txt
ai_podcast_generator-0.1.0.dist-info/RECORD
