Metadata-Version: 2.4
Name: ai-podcast-generator
Version: 0.1.0
Summary: A Python package to generate AI-powered podcasts in Hindi, Marathi, or English using Gemini API.
Author-email: Harsh Moreshwar Kale <harshmkale.2004@gmail.com>
License: MIT
Project-URL: Homepage, https://github.com/Harshk133/ai_podcast_generator
Project-URL: Repository, https://github.com/Harshk133/ai_podcast_generator.git
Project-URL: Issues, https://github.com/Harshk133/ai_podcast_generator/issues
Keywords: podcast,ai,text-to-speech,gemini,hindi,marathi,english
Classifier: Programming Language :: Python :: 3
Classifier: License :: OSI Approved :: MIT License
Classifier: Operating System :: OS Independent
Requires-Python: >=3.10
License-File: LICENSE
Requires-Dist: pyaudio>=0.2.17
Requires-Dist: pydub>=0.25.1
Requires-Dist: google-generativeai>=2.0.0
Dynamic: license-file
